simple_capture/__init__.py
simple_capture/__main__.py
simple_capture/utils.py
simple_capture/config/__init__.py
simple_capture/config/cli.py
simple_capture/config/commands.py
simple_capture/config/io.py
simple_capture/source/__init__.py
simple_capture/source/devices.py
simple_capture/source/filters.py
simple_capture/source/global_options.py
simple_capture/source/input_devices.py
simple_capture/source/input_streams.py
simple_capture/source/output_devices.py
simple_capture/source/output_streams.py
simple_capture/source/streams.py
simple_capture-1.0.dist-info/LICENSE.txt
simple_capture-1.0.dist-info/METADATA
simple_capture-1.0.dist-info/WHEEL
simple_capture-1.0.dist-info/dependency_links.txt
simple_capture-1.0.dist-info/entry_points.txt
simple_capture-1.0.dist-info/top_level.txt
simple_capture-1.0.dist-info/RECORD
