Metadata-Version: 2.1
Name: simple-capture
Version: 1.0
Summary: Command line screen recorder, built using FFmpeg.
Home-page: https://github.com/Raj-CSH/simple-capture
Author: Rajarshi Mandal
License: BSD 2-Clause License
Keywords: ffmpeg,record,capture,screen,broadcast,stream
Platform: UNKNOWN
Classifier: Programming Language :: Python :: 3
Classifier: Programming Language :: Python :: 3.8
Classifier: License :: OSI Approved :: BSD License
Classifier: Environment :: Console
Requires-Python: >=3.7
Requires-Dist: click (==7.1.2)
Requires-Dist: ffmpeg-python (==0.2.0)
Requires-Dist: screeninfo (==0.6.5)
